django_query_fetch/__init__.py
django_query_fetch/query_fetch.py
django_query_fetch-0.0.1.dist-info/LICENSE
django_query_fetch-0.0.1.dist-info/METADATA
django_query_fetch-0.0.1.dist-info/WHEEL
django_query_fetch-0.0.1.dist-info/top_level.txt
django_query_fetch-0.0.1.dist-info/RECORD
